txdatadog/__init__.py
txdatadog/client.py
txdatadog/metrics.py
txdatadog/tests/__init__.py
txdatadog/tests/fakes.py
txdatadog/tests/strategies.py
txdatadog/tests/test_fakes.py
txdatadog/tests/test_metrics.py
txdatadog-1.3.0.dist-info/COPYING
txdatadog-1.3.0.dist-info/METADATA
txdatadog-1.3.0.dist-info/WHEEL
txdatadog-1.3.0.dist-info/top_level.txt
txdatadog-1.3.0.dist-info/RECORD
