Metadata-Version: 2.1
Name: txdatadog
Version: 1.3.0
Summary: Datadog statsd APIs for Twisted
Home-page: https://github.com/Julian/txdatadog
Author: Julian Berman
Author-email: Julian+txdatadog@GrayVines.com
License: UNKNOWN
Project-URL: Source, https://github.com/Julian/txdatadog
Project-URL: Issues, https://github.com/Julian/txdatadog/issues/
Platform: UNKNOWN
Classifier: Development Status :: 3 - Alpha
Classifier: Operating System :: OS Independent
Classifier: Programming Language :: Python
Classifier: License :: OSI Approved :: MIT License
Classifier: Programming Language :: Python :: 2.7
Classifier: Programming Language :: Python :: 2
Classifier: Programming Language :: Python :: Implementation :: PyPy
Requires-Dist: attrs (>=17.1.0)
Requires-Dist: cached-property
Requires-Dist: importlib-metadata
Requires-Dist: pyrsistent
Requires-Dist: twisted
